{"none": 99, "produto": 98, "nao": 97, "entregar": 96, "prazo": 95, "muito": 94, "comprar": 93, "antar": 92, "bom": 91, "chegar": 90, "receber": 89, "vir": 88, "bem": 87, "recomendar": 86, "qualidade": 85, "loja": 84, "ter": 83, "rapido": 82, "ainda": 81, "dia": 80, "mais": 79, "pedir": 78, "so": 77, "excelente": 76, "recebi": 75, "ja": 74, "super": 73, "dentro": 72, "fazer": 71, "chegou": 70, "otimo": 69, "recomendo": 68, "entrega": 67, "esperar": 66, "comprei": 65, "site": 64, "gostar": 63, "mesmo": 62, "problema": 61, "lannister": 60, "otima": 59, "ficar": 58, "sempre": 57, "agora": 56, "apenas": 55, "embalar": 54, "gostei": 53, "poder": 52, "enviar": 51, "prever": 50, "dar": 49, "perfazer": 48, "aguardar": 47, "demorar": 46, "datar": 45, "ser": 44, "saber": 43, "satisfeito": 42, "atendimento": 41, "corretar": 40, "preco": 39, "errar": 38, "noto": 37, "querer": 36, "usar": 35, "bonito": 34, "foto": 33, "pagar": 32, "tempo": 31, "trocar": 30, "achar": 29, "estar": 28, "correio": 27, "contato": 26, "certar": 25, "parabens": 24, "fretar": 23, "cor": 22, "funcionar": 21, "empresar": 20, "expectativa": 19, "diferente": 18, "dever": 17, "caixa": 16, "satisfazer": 15, "mercadoria": 14, "vendedor": 13, "anunciar": 12, "entregue": 11, "relogio": 10, "embalagem": 9, "pouco": 8, "cliente": 7, "material": 6, "faltar": 5, "momento": 4, "comer": 3, "lindar": 2, "dizer": 1}